SimpleLanguage/__init__.py
SimpleLanguage/code_exceptions.py
SimpleLanguage/code_helper.py
SimpleLanguage/code_main.py
SimpleLanguage-0.2.0.dist-info/LICENSE
SimpleLanguage-0.2.0.dist-info/METADATA
SimpleLanguage-0.2.0.dist-info/WHEEL
SimpleLanguage-0.2.0.dist-info/top_level.txt
SimpleLanguage-0.2.0.dist-info/RECORD
