Metadata-Version: 2.1
Name: SimpleLanguage
Version: 0.2.0
Summary: Multi language tool for python
Home-page: https://github.com/Acuf5928/SimpleLanguage
Author: Acuf5928
Author-email: alberto.cuffaro@hotmail.it
License: UNKNOWN
Platform: UNKNOWN
Classifier: Programming Language :: Python :: 3
Classifier: License :: OSI Approved :: MIT License
Classifier: Operating System :: OS Independent
Requires-Python: >=3.6
